MusicDownloader/MusicDownloader.py
MusicDownloader/__init__.py
MusicDown-0.1.0.dist-info/METADATA
MusicDown-0.1.0.dist-info/WHEEL
MusicDown-0.1.0.dist-info/top_level.txt
MusicDown-0.1.0.dist-info/RECORD
